resolva/__init__.py
resolva/resolver.py
resolva/template.py
resolva/utils.py
resolva-0.0.1.dist-info/METADATA
resolva-0.0.1.dist-info/WHEEL
resolva-0.0.1.dist-info/licenses/LICENSE
resolva-0.0.1.dist-info/RECORD
