Metadata-Version: 2.1
Name: resolva
Version: 0.0.1
Summary: Simple and fast path template resolver.
Project-URL: Homepage, https://github.com/MichaelHaussmann/resolva
Author-email: Michael Haussmann <spil@xeo.info>
License: MIT License
License-File: LICENSE
Keywords: path templates
Classifier: Development Status :: 4 - Beta
Classifier: Intended Audience :: Developers
Classifier: License :: OSI Approved :: MIT License
Classifier: Natural Language :: English
Classifier: Operating System :: OS Independent
Classifier: Programming Language :: Python
Classifier: Programming Language :: Python :: 3
Classifier: Programming Language :: Python :: 3.7
Classifier: Topic :: Software Development
Classifier: Topic :: Software Development :: Libraries
Requires-Python: >=3.7
Provides-Extra: dev
Requires-Dist: pytest; extra == 'dev'
